leaguepediadb/__init__.py
leaguepediadb/dbapi.py
python_leaguepedia_db-0.1.1b1.dist-info/LICENSE
python_leaguepedia_db-0.1.1b1.dist-info/METADATA
python_leaguepedia_db-0.1.1b1.dist-info/WHEEL
python_leaguepedia_db-0.1.1b1.dist-info/top_level.txt
python_leaguepedia_db-0.1.1b1.dist-info/RECORD
