Metadata-Version: 2.1
Name: python-leaguepedia-db
Version: 0.1.1b1
Summary: Python DB-API Adaptor for Leaguepedia
Home-page: https://github.com/kyujin-cho/pyhton-leaguepedia-db
Author: Kyujin Cho
Author-email: thy2134@gmail.com
License: Apache License 2.0
Project-URL: Documentation, https://github.com/kyujin-cho/pyhton-leaguepedia-db
Project-URL: Source, https://github.com/kyujin-cho/pyhton-leaguepedia-db
Project-URL: Tracker, https://github.com/kyujin-cho/pyhton-leaguepedia-db/issues
Platform: UNKNOWN
Classifier: Development Status :: 4 - Beta
Classifier: License :: OSI Approved :: GNU General Public License v3 or later (GPLv3+)
Classifier: Intended Audience :: Developers
Classifier: Programming Language :: Python
Classifier: Programming Language :: Python :: 3
Classifier: Programming Language :: Python :: 3.9
Classifier: Operating System :: POSIX
Classifier: Operating System :: MacOS :: MacOS X
Classifier: Topic :: Software Development
Requires-Python: >=3.9
License-File: LICENSE
Requires-Dist: mwclient (~=0.10.1)
Requires-Dist: mo-sql-parsing (~=8.145.22062)
Provides-Extra: build
Requires-Dist: wheel (>=0.36.2) ; extra == 'build'
Requires-Dist: twine (>=3.4.1) ; extra == 'build'
Provides-Extra: dev
Provides-Extra: lint
Requires-Dist: flake8 (>=4.0.1) ; extra == 'lint'
Requires-Dist: flake8-commas (>=2.1) ; extra == 'lint'
Provides-Extra: test
Requires-Dist: pytest (~=6.2.5) ; extra == 'test'
Requires-Dist: pytest-asyncio (~=0.16.0) ; extra == 'test'
Requires-Dist: pytest-cov (>=2.11) ; extra == 'test'
Requires-Dist: pytest-mock (>=3.5.0) ; extra == 'test'
Requires-Dist: codecov ; extra == 'test'
Provides-Extra: typecheck
Requires-Dist: mypy (>=0.930) ; extra == 'typecheck'
